README.md
setup.cfg
setup.py
op1repacker/__init__.py
op1repacker/main.py
op1repacker/op1_analyze.py
op1repacker/op1_db.py
op1repacker/op1_gfx.py
op1repacker/op1_patches.py
op1repacker/op1_repack.py
op1repacker.egg-info/PKG-INFO
op1repacker.egg-info/SOURCES.txt
op1repacker.egg-info/dependency_links.txt
op1repacker.egg-info/entry_points.txt
op1repacker.egg-info/requires.txt
op1repacker.egg-info/top_level.txt
op1repacker/assets/display/cwo-moose.patch.json
op1repacker/assets/display/iter-lab.svg
op1repacker/assets/display/tape-invert.patch.json
op1repacker/assets/presets/iter/crystal_pad.aif
op1repacker/assets/presets/iter/ebullition.aif
op1repacker/assets/presets/iter/feu_doux.aif
op1repacker/assets/presets/iter/iter.aif
op1repacker/assets/presets/iter/korder.aif
op1repacker/assets/presets/iter/lotremkords.aif
op1repacker/assets/presets/iter/pulse_bass.aif
op1repacker/assets/presets/iter/rezpiano.aif
op1repacker/assets/presets/iter/wonky_bass.aif
op1repacker/assets/presets/iter/wood_bell.aif
op1repacker/assets/presets/iter/woodblock.aif