Metadata-Version: 1.0
Name: op1repacker
Version: 0.2.6
Summary: Tool for unpacking, modding and repacking OP-1 firmware.
Home-page: https://github.com/op1hacks/op1repacker/
Author: Richard Lewis
Author-email: richrd.lewis@gmail.com
License: UNKNOWN
Platform: UNKNOWN
